weight_conversion/__init__.py
weight_conversion/kg_to_pounds.py
weight_conversion/pounds_to_kg.py
Weight_convertor-1.0.dist-info/METADATA
Weight_convertor-1.0.dist-info/WHEEL
Weight_convertor-1.0.dist-info/license
Weight_convertor-1.0.dist-info/top_level.txt
Weight_convertor-1.0.dist-info/RECORD
